robotkinematicscatalogue/__init__.py
robotkinematicscatalogue/angleSetConventions.py
robotkinematicscatalogue/forwardKinematics.py
robotkinematicscatalogue/source.py
robotkinematicscatalogue/synthesize.py
robotkinematicscatalogue/trajectoryGeneration.py
robotkinematicscatalogue/inversekinematics/SCARA.py
robotkinematicscatalogue/inversekinematics/__init__.py
robotkinematicscatalogue/inversekinematics/collaborativeRobots.py
robotkinematicscatalogue/inversekinematics/fiveDOF.py
robotkinematicscatalogue/inversekinematics/industrialRobots.py
robotkinematicscatalogue/inversekinematics/misc.py
robotkinematicscatalogue/inversekinematics/palletizing.py
robotkinematicscatalogue/inversekinematics/sevenDOF.py
robotkinematicscatalogue/inversekinematics/__1DOF/ABB_IRBP_L300_L1250.py
robotkinematicscatalogue/inversekinematics/__1DOF/ABB_IRBT_4004_Standard_20m.py
robotkinematicscatalogue/inversekinematics/__1DOF/Motoman_MSR_355.py
robotkinematicscatalogue/inversekinematics/__1DOF/__init__.py
robotkinematicscatalogue/inversekinematics/__2DOF/ABB_IRBP_A250_D1000.py
robotkinematicscatalogue/inversekinematics/__2DOF/ABB_IRBP_A500_D1000_H700.py
robotkinematicscatalogue/inversekinematics/__2DOF/ABB_IRBP_A500_D1000_H900.py
robotkinematicscatalogue/inversekinematics/__2DOF/ABB_IRBP_A500_D1450_H700.py
robotkinematicscatalogue/inversekinematics/__2DOF/ABB_IRBP_A500_D1450_H900.py
robotkinematicscatalogue/inversekinematics/__2DOF/ABB_IRBP_A750_D1000_H700.py
robotkinematicscatalogue/inversekinematics/__2DOF/ABB_IRBP_A750_D1000_H900.py
robotkinematicscatalogue/inversekinematics/__2DOF/API_OT2_Laser_Tracker.py
robotkinematicscatalogue/inversekinematics/__2DOF/KUKA_DKP_400.py
robotkinematicscatalogue/inversekinematics/__2DOF/KUKA_KP2_HV500.py
robotkinematicscatalogue/inversekinematics/__2DOF/KUKA_KP2_SV2600_HW.py
robotkinematicscatalogue/inversekinematics/__2DOF/Lucas_RC2_YZ_1R.py
robotkinematicscatalogue/inversekinematics/__2DOF/Motoman_MT1_500_S2HD.py
robotkinematicscatalogue-1.1.2.dist-info/LICENSE
robotkinematicscatalogue-1.1.2.dist-info/METADATA
robotkinematicscatalogue-1.1.2.dist-info/WHEEL
robotkinematicscatalogue-1.1.2.dist-info/top_level.txt
robotkinematicscatalogue-1.1.2.dist-info/RECORD
