Metadata-Version: 2.1
Name: robotkinematicscatalogue
Version: 1.1.2
Summary: Closed-form Inverse Kinematic Solutions, Forward Kinematics, and Trajectory Generation in one repository
Home-page: UNKNOWN
Author: Mathias Lykholt-Ustrup
Author-email: <saltworkermlu@gmail.com>
License: UNKNOWN
Platform: UNKNOWN
Requires-Dist: scipy
Requires-Dist: numpy
Requires-Dist: sympy
Requires-Dist: matplotlib
